async_tail-0.2.0.dist-info/METADATA
async_tail-0.2.0.dist-info/WHEEL
async_tail-0.2.0.dist-info/license_files/LICENSE
async_tail/py.typed
async_tail/version.py
async_tail/_async_tail.pyi
async_tail/main.py
async_tail/__init__.py
async_tail/_async_tail.cpython-38-powerpc64le-linux-gnu.so
async_tail-0.2.0.dist-info/RECORD
