Metadata-Version: 2.1
Name: async-tail
Version: 0.2.0
Classifier: Development Status :: 3 - Alpha
Classifier: Programming Language :: Rust
Classifier: Programming Language :: Python :: Implementation :: CPython
Classifier: Programming Language :: Python :: Implementation :: PyPy
Classifier: Programming Language :: Python :: 3
Classifier: Programming Language :: Python :: 3 :: Only
Classifier: Programming Language :: Python :: 3.7
Classifier: Programming Language :: Python :: 3.8
Classifier: Programming Language :: Python :: 3.9
Classifier: Programming Language :: Python :: 3.10
Classifier: Programming Language :: Python :: 3.11
Classifier: Intended Audience :: Developers
Classifier: Intended Audience :: Information Technology
Classifier: Intended Audience :: System Administrators
Classifier: License :: OSI Approved :: MIT License
Classifier: Operating System :: POSIX :: Linux
Classifier: Operating System :: Microsoft :: Windows
Classifier: Operating System :: MacOS
Classifier: Environment :: MacOS X
Classifier: Topic :: Software Development :: Libraries :: Python Modules
Classifier: Topic :: System :: Filesystems
License-File: LICENSE
Summary: tail -f utility library providing both sync and async interfaces
Home-Page: https://github.com/TheoBabilon/async-tail
Author-email: Theo BABILON <theo.babilon@gmail.com>
License: MIT
Requires-Python: >=3.7
Project-URL: Homepage, https://github.com/theobabilon/async-tail
Project-URL: Funding, https://github.com/sponsors/theobabilon
Project-URL: Source, https://github.com/theobabilon/async-tail
